openapi_annotations/__init__.py
openapi_annotations/decorators.py
openapi_annotations/globals.py
openapi_annotations/methods.py
openapi_annotations/parameter_types.py
openapi_annotations/schema.py
openapi_annotations/spec_generator.py
openapi_annotations/string_formats.py
openapi_annotations-0.1.2.dist-info/LICENSE
openapi_annotations-0.1.2.dist-info/WHEEL
openapi_annotations-0.1.2.dist-info/METADATA
openapi_annotations-0.1.2.dist-info/RECORD
